README.rst
setup.cfg
setup.py
scrapy_html_storage/__init__.py
scrapy_html_storage/filesys.py
scrapy_html_storage.egg-info/PKG-INFO
scrapy_html_storage.egg-info/SOURCES.txt
scrapy_html_storage.egg-info/dependency_links.txt
scrapy_html_storage.egg-info/not-zip-safe
scrapy_html_storage.egg-info/top_level.txt