Metadata-Version: 1.0
Name: scrapy-html-storage
Version: 0.3.0
Summary: Scrapy downloader middleware that stores response HTML files to disk.
Home-page: https://github.com/povilasb/scrapy-html-storage
Author: Povilas Balciunas
Author-email: balciunas90@gmail.com
License: MIT
Platform: UNKNOWN
